{"data":[{"lang":"es","id":"1319854726910005254","created_at":"2020-10-24T04:14:23.000Z","text":"RT @Alvisepf: Mientras @PabloIglesias se inventaba un caso de acoso sexual para ocultar sus delitos y daba órdenes de no investigar la expl…"},{"lang":"es","id":"1319854692529307648","created_at":"2020-10-24T04:14:15.000Z","text":"RT @Flugbeiler: Never forget que todas las cabezas visibles del feminismo podemita participaron con gusto en una falsa acusación por acoso…"},{"lang":"es","id":"1319854647704768512","created_at":"2020-10-24T04:14:04.000Z","text":"Leía tantas noticas de acoso y pensaba \"pucha que pendejada, espero que todas estén bien\", piensas de otra manera cuando te pasa. Ahora tienes cierto temor y más trauma de salir sola :'v"},{"lang":"es","id":"1319854641467805703","created_at":"2020-10-24T04:14:02.000Z","text":"RT @yorkymarfiguer1: A pesar del acoso que nos tienen con el internet, la luz, el gas, las redes y muchas cosas más, aquí estoy y así voy #…"},{"lang":"es","id":"1319854597805117440","created_at":"2020-10-24T04:13:52.000Z","text":"RT @PamelaCDMX: El acoso a medios, esto es una amenaza a la libertad en México, no es ningún logro. Enfermos! https://t.co/pWCdYTA7Yn"},{"lang":"es","id":"1319854512614658048","created_at":"2020-10-24T04:13:32.000Z","text":"RT @gabiestevezok: Un 23 de octubre como hoy, hace 9 años, Cristina Kirchner obtenía el 54% de los votos y se convertía en la primera mujer…"},{"lang":"es","id":"1319854492758822913","created_at":"2020-10-24T04:13:27.000Z","text":"RT @RiveraMarioCDMX: \uD83D\uDC4D @Notimex recuerda que tras movimiento #MeToo, “Toy Story 2” eliminó escena de \"acoso\" - #Notimex #Espectaculos #MeTo…"},{"lang":"es","id":"1319854479328505857","created_at":"2020-10-24T04:13:24.000Z","text":"RT @CarrascosaCris_: Despedir a tu abogado por falso acoso sexual, pero tener un Ministerio de Igualdad, pero robarle la SIM a una compañer…"},{"lang":"es","id":"1319854400068898816","created_at":"2020-10-24T04:13:05.000Z","text":"RT @yorkymarfiguer1: A pesar del acoso que nos tienen con el internet, la luz, el gas, las redes y muchas cosas más, aquí estoy y así voy #…"},{"lang":"es","id":"1319854385896263682","created_at":"2020-10-24T04:13:01.000Z","text":"RT @redlgbtcig: Comunicado sobre las amenazas y el acoso contra personas y establecimientos LGBTI+\n\nFirman Resitencia No Binarix junto a má…"}],"meta":{"newest_id":"1319854726910005254","oldest_id":"1319854385896263682","result_count":10,"next_token":"b26v89c19zqg8o3fos8w5su562ubpmbl25ixmjus86gsd"}}