{"data":[{"lang":"es","id":"1320015991225667590","created_at":"2020-10-24T14:55:11.000Z","text":"RT @FormulaTV: \uD83D\uDC9B1⃣ El abrumador apoyo en redes que el personaje de Eva recibió cuando en #HastaSiempreSKAMEspaña sufrió ciberacoso. ¡Los fa…"},{"lang":"es","id":"1320015574349631490","created_at":"2020-10-24T14:53:32.000Z","text":"@figaheath hilo de llamamiento a @figaheath por ejercicio de ciberacoso debilerado"},{"lang":"es","id":"1320015558172180481","created_at":"2020-10-24T14:53:28.000Z","text":"RT @sergiourregoorg: 7) Por otro lado, si es tu amigo/a el que está siendo víctima del ciberacoso, lo importante es que escuches, porque po…"},{"lang":"es","id":"1320015192789520384","created_at":"2020-10-24T14:52:01.000Z","text":"RT @sergiourregoorg: ¡Paremos el ciberacoso! Si sientes que te acosan o insultan por redes sociales, en un videojuego o demás plataformas d…"},{"lang":"es","id":"1320014914854002688","created_at":"2020-10-24T14:50:55.000Z","text":"RT @sergiourregoorg: ¡Paremos el ciberacoso! Si sientes que te acosan o insultan por redes sociales, en un videojuego o demás plataformas d…"},{"lang":"es","id":"1320012714454953987","created_at":"2020-10-24T14:42:10.000Z","text":"Alguien sabe el teléfono para el ciberacoso? @ policia ? https://t.co/mgmypRjCeJ"},{"lang":"es","id":"1320012500151271427","created_at":"2020-10-24T14:41:19.000Z","text":"RT @PorunaCarrera: Dada la pandemia, uso de redes sociales ha aumentado un 70% según estudios, así como también las cifras de #ciberbullyin…"},{"lang":"es","id":"1320012309109112832","created_at":"2020-10-24T14:40:33.000Z","text":"RT @PorunaCarrera: Dada la pandemia, uso de redes sociales ha aumentado un 70% según estudios, así como también las cifras de #ciberbullyin…"},{"lang":"es","id":"1320006070660698113","created_at":"2020-10-24T14:15:46.000Z","text":"RT @FSummerCL: Si estas sufriendo de ciberacoso o conoces a alguien que esté siendo víctima de ciberacoso, aquí te entregamos herramientas…"},{"lang":"es","id":"1320005578731737088","created_at":"2020-10-24T14:13:49.000Z","text":"RT @sandrabtrigo: Agradezco ❤ la oportunidad de poner en nuestra agenda pública este tema tan complejo y que requiere de todos, Estado y So…"},{"lang":"es","id":"1320005232554815490","created_at":"2020-10-24T14:12:26.000Z","text":"RT @sociosbocajrs: ➡️ Taller sobre #Grooming (Ciberacoso Sexual Infantil) Prevención y Concientización.\n\nDesde la Secretaría de Desarrollo…"},{"lang":"es","id":"1320003601981411328","created_at":"2020-10-24T14:05:57.000Z","text":"RT @FSummerCL: Si estas sufriendo de ciberacoso o conoces a alguien que esté siendo víctima de ciberacoso, aquí te entregamos herramientas…"},{"lang":"es","id":"1320003320128458759","created_at":"2020-10-24T14:04:50.000Z","text":"#Tamaulipas \nAprueba el @CongresoTams  la ´Ley Olimpia´.\n\n▶️ https://t.co/4iv6pCMo3D https://t.co/tB2RQ0xAsm"},{"lang":"es","id":"1320003282534891520","created_at":"2020-10-24T14:04:41.000Z","text":"#Tamaulipas \nAprueba el @CongresoTams  la ´Ley Olimpia´.\n\n▶️ https://t.co/3zFLByzrHu https://t.co/9yNcMQrTlg"},{"lang":"es","id":"1320002815373303808","created_at":"2020-10-24T14:02:50.000Z","text":"@Lord_Tiberius Es que del mundo LOL no tengo ni idea, nunca he jugado a eso ni me llama la atención xDD\n\nYo recuerdo que le hicieron  ciberacoso a una chica (creo que era coreana) por participar en un torneo de LOL, así que no me extraña, hay mucho gaymers machistas en la comunidad..."},{"lang":"es","id":"1320002104782508032","created_at":"2020-10-24T14:00:00.000Z","text":"#Sociedad \n\n\uD83D\uDCDC\uD83D\uDCF2❗️ Hasta 1.7 mdp de multa y 11 años de cárcel a los responsables delitos sexuales por internet\n\n#LeyOlimpia #Combate #Ciberacoso #Multas \n\nhttps://t.co/ndiM4GKzWi"},{"lang":"es","id":"1320001733368664064","created_at":"2020-10-24T13:58:32.000Z","text":"RT @FSummerCL: Si estas sufriendo de ciberacoso o conoces a alguien que esté siendo víctima de ciberacoso, aquí te entregamos herramientas…"},{"lang":"es","id":"1320000536196907009","created_at":"2020-10-24T13:53:46.000Z","text":"RT @FSummerCL: Si estas sufriendo de ciberacoso o conoces a alguien que esté siendo víctima de ciberacoso, aquí te entregamos herramientas…"},{"lang":"es","id":"1320000297796800515","created_at":"2020-10-24T13:52:50.000Z","text":"RT @FSummerCL: Si estas sufriendo de ciberacoso o conoces a alguien que esté siendo víctima de ciberacoso, aquí te entregamos herramientas…"},{"lang":"es","id":"1320000128199970816","created_at":"2020-10-24T13:52:09.000Z","text":"El castigo a los delitos de ciberacoso y violación a la intimidad fueron aprobados en #Tamaulipas y #Chihuahua, con lo que suman ya 26 estados que sancionan estos crímenes a través de la denominada #LeyOlimpia.\n\nhttps://t.co/RLLAXC5nJq"},{"lang":"es","id":"1319997890438270978","created_at":"2020-10-24T13:43:16.000Z","text":"RT @FSummerCL: Si estas sufriendo de ciberacoso o conoces a alguien que esté siendo víctima de ciberacoso, aquí te entregamos herramientas…"},{"lang":"es","id":"1319997717800751107","created_at":"2020-10-24T13:42:34.000Z","text":"RT @IvettBermeaMX: Las #Diputadas de #AcciónNacional  SI cumplimos para defender la dignidad de las personas contra el #Ciberacoso y la #Vi…"},{"lang":"es","id":"1319992047873515520","created_at":"2020-10-24T13:20:03.000Z","text":"RT @FSummerCL: Si estas sufriendo de ciberacoso o conoces a alguien que esté siendo víctima de ciberacoso, aquí te entregamos herramientas…"},{"lang":"es","id":"1319991862040711170","created_at":"2020-10-24T13:19:18.000Z","text":"RT @FSummerCL: Si estas sufriendo de ciberacoso o conoces a alguien que esté siendo víctima de ciberacoso, aquí te entregamos herramientas…"},{"lang":"es","id":"1319989254341222401","created_at":"2020-10-24T13:08:57.000Z","text":"RT @FSummerCL: Si estas sufriendo de ciberacoso o conoces a alguien que esté siendo víctima de ciberacoso, aquí te entregamos herramientas…"},{"lang":"es","id":"1319987796782780417","created_at":"2020-10-24T13:03:09.000Z","text":"RT @MiguelPTIC: \uD83D\uDD34 Si eres víctima de acciones hostiles, repetidas y deliberadas en redes sociales, no dudes en reportar y denunciar por #Ci…"},{"lang":"es","id":"1319985129457057792","created_at":"2020-10-24T12:52:33.000Z","text":"RT @FSummerCL: Si estas sufriendo de ciberacoso o conoces a alguien que esté siendo víctima de ciberacoso, aquí te entregamos herramientas…"},{"lang":"es","id":"1319984346028298242","created_at":"2020-10-24T12:49:26.000Z","text":"RT @FSummerCL: Si estas sufriendo de ciberacoso o conoces a alguien que esté siendo víctima de ciberacoso, aquí te entregamos herramientas…"},{"lang":"es","id":"1319980560341762048","created_at":"2020-10-24T12:34:24.000Z","text":"RT @sergiourregoorg: ¡Paremos el ciberacoso! Si sientes que te acosan o insultan por redes sociales, en un videojuego o demás plataformas d…"},{"lang":"es","id":"1319978645365182464","created_at":"2020-10-24T12:26:47.000Z","text":"RT @FormulaTV: \uD83D\uDC9B1⃣ El abrumador apoyo en redes que el personaje de Eva recibió cuando en #HastaSiempreSKAMEspaña sufrió ciberacoso. ¡Los fa…"},{"lang":"es","id":"1319974116171153409","created_at":"2020-10-24T12:08:47.000Z","text":"RT @FormulaTV: \uD83D\uDC9B1⃣ El abrumador apoyo en redes que el personaje de Eva recibió cuando en #HastaSiempreSKAMEspaña sufrió ciberacoso. ¡Los fa…"},{"lang":"es","id":"1319973702340087808","created_at":"2020-10-24T12:07:09.000Z","text":"RT @sociosbocajrs: ➡️ Taller sobre #Grooming (Ciberacoso Sexual Infantil) Prevención y Concientización.\n\nDesde la Secretaría de Desarrollo…"},{"lang":"es","id":"1319969853470658560","created_at":"2020-10-24T11:51:51.000Z","text":"RT @FormulaTV: \uD83D\uDC9B1⃣ El abrumador apoyo en redes que el personaje de Eva recibió cuando en #HastaSiempreSKAMEspaña sufrió ciberacoso. ¡Los fa…"},{"lang":"es","id":"1319965293851140097","created_at":"2020-10-24T11:33:44.000Z","text":"RT @FormulaTV: \uD83D\uDC9B1⃣ El abrumador apoyo en redes que el personaje de Eva recibió cuando en #HastaSiempreSKAMEspaña sufrió ciberacoso. ¡Los fa…"},{"lang":"es","id":"1319964453174153216","created_at":"2020-10-24T11:30:24.000Z","text":"Dos de cada tres niñas sufren ciberacoso en redes sociales https://t.co/lFkLxY7Ar9 por @PandaComunica #ciberseguridad #acoso #redessociales #actualidad https://t.co/YMW1KI7zLt"},{"lang":"es","id":"1319964074025885696","created_at":"2020-10-24T11:28:53.000Z","text":"RT @FormulaTV: \uD83D\uDC9B1⃣ El abrumador apoyo en redes que el personaje de Eva recibió cuando en #HastaSiempreSKAMEspaña sufrió ciberacoso. ¡Los fa…"},{"lang":"es","id":"1319960258782048256","created_at":"2020-10-24T11:13:44.000Z","text":"RT @FormulaTV: \uD83D\uDC9B1⃣ El abrumador apoyo en redes que el personaje de Eva recibió cuando en #HastaSiempreSKAMEspaña sufrió ciberacoso. ¡Los fa…"},{"lang":"es","id":"1319959860784603136","created_at":"2020-10-24T11:12:09.000Z","text":"RT @FormulaTV: \uD83D\uDC9B1⃣ El abrumador apoyo en redes que el personaje de Eva recibió cuando en #HastaSiempreSKAMEspaña sufrió ciberacoso. ¡Los fa…"},{"lang":"es","id":"1319959092945969152","created_at":"2020-10-24T11:09:06.000Z","text":"RT @FormulaTV: \uD83D\uDC9B1⃣ El abrumador apoyo en redes que el personaje de Eva recibió cuando en #HastaSiempreSKAMEspaña sufrió ciberacoso. ¡Los fa…"},{"lang":"es","id":"1319959081210302469","created_at":"2020-10-24T11:09:03.000Z","text":"RT @FormulaTV: \uD83D\uDC9B1⃣ El abrumador apoyo en redes que el personaje de Eva recibió cuando en #HastaSiempreSKAMEspaña sufrió ciberacoso. ¡Los fa…"},{"lang":"es","id":"1319958253950930946","created_at":"2020-10-24T11:05:46.000Z","text":"RT @FormulaTV: \uD83D\uDC9B1⃣ El abrumador apoyo en redes que el personaje de Eva recibió cuando en #HastaSiempreSKAMEspaña sufrió ciberacoso. ¡Los fa…"},{"lang":"es","id":"1319958122509762560","created_at":"2020-10-24T11:05:14.000Z","text":"RT @FormulaTV: \uD83D\uDC9B1⃣ El abrumador apoyo en redes que el personaje de Eva recibió cuando en #HastaSiempreSKAMEspaña sufrió ciberacoso. ¡Los fa…"},{"lang":"es","id":"1319955977735647232","created_at":"2020-10-24T10:56:43.000Z","text":"RT @FormulaTV: \uD83D\uDC9B1⃣ El abrumador apoyo en redes que el personaje de Eva recibió cuando en #HastaSiempreSKAMEspaña sufrió ciberacoso. ¡Los fa…"},{"lang":"es","id":"1319952308692787200","created_at":"2020-10-24T10:42:08.000Z","text":"RT @FormulaTV: \uD83D\uDC9B1⃣ El abrumador apoyo en redes que el personaje de Eva recibió cuando en #HastaSiempreSKAMEspaña sufrió ciberacoso. ¡Los fa…"},{"lang":"es","id":"1319951502526611456","created_at":"2020-10-24T10:38:56.000Z","text":"RT @FormulaTV: \uD83D\uDC9B1⃣ El abrumador apoyo en redes que el personaje de Eva recibió cuando en #HastaSiempreSKAMEspaña sufrió ciberacoso. ¡Los fa…"},{"lang":"es","id":"1319951400282062848","created_at":"2020-10-24T10:38:31.000Z","text":"RT @FormulaTV: \uD83D\uDC9B1⃣ El abrumador apoyo en redes que el personaje de Eva recibió cuando en #HastaSiempreSKAMEspaña sufrió ciberacoso. ¡Los fa…"},{"lang":"es","id":"1319945683563171840","created_at":"2020-10-24T10:15:49.000Z","text":"RT @FormulaTV: \uD83D\uDC9B1⃣ El abrumador apoyo en redes que el personaje de Eva recibió cuando en #HastaSiempreSKAMEspaña sufrió ciberacoso. ¡Los fa…"},{"lang":"es","id":"1319945579884064769","created_at":"2020-10-24T10:15:24.000Z","text":"RT @FormulaTV: \uD83D\uDC9B1⃣ El abrumador apoyo en redes que el personaje de Eva recibió cuando en #HastaSiempreSKAMEspaña sufrió ciberacoso. ¡Los fa…"},{"lang":"es","id":"1319945453006475264","created_at":"2020-10-24T10:14:54.000Z","text":"RT @FormulaTV: \uD83D\uDC9B1⃣ El abrumador apoyo en redes que el personaje de Eva recibió cuando en #HastaSiempreSKAMEspaña sufrió ciberacoso. ¡Los fa…"},{"lang":"es","id":"1319945229919834112","created_at":"2020-10-24T10:14:00.000Z","text":"RT @sergiourregoorg: ¡Paremos el ciberacoso! Si sientes que te acosan o insultan por redes sociales, en un videojuego o demás plataformas d…"}],"meta":{"newest_id":"1320015991225667590","oldest_id":"1319945229919834112","result_count":50,"next_token":"b26v89c19zqg8o3fos8w5uykkhtz4ij9dwevf40vjhegt"}}